tringocircle/__init__.py
tringocircle/filecore/__init__.py
tringocircle/filecore/fill.py
tringocircle-0.1.0.dist-info/WHEEL
tringocircle-0.1.0.dist-info/METADATA
tringocircle-0.1.0.dist-info/RECORD
