Metadata-Version: 2.4
Name: tringocircle
Version: 0.1.0
Summary: A library for drawing circle patterns with turtle graphics.
Author-email: Your Name <your@email.com>
Project-URL: Home, https://github.com/yourusername/tringocircle
